amv7/cli.py
amv7/x64/amv7.py
amv7/x64/pytransform/__init__.py
amv7/x64/pytransform/_pytransform.so
amv7/x64/pytransform/license.lic
amv7/x64/pytransform/pytransform.key
amv7/x86/amv7.py
amv7/x86/pytransform/__init__.py
amv7/x86/pytransform/_pytransform.so
amv7/x86/pytransform/license.lic
amv7/x86/pytransform/pytransform.key
amv7-1.0.6.dist-info/LICENSE
amv7-1.0.6.dist-info/METADATA
amv7-1.0.6.dist-info/WHEEL
amv7-1.0.6.dist-info/entry_points.txt
amv7-1.0.6.dist-info/top_level.txt
amv7-1.0.6.dist-info/RECORD
